spectran/__init__.py
spectran/__main__.py
spectran/_version.py
spectran/api.py
spectran/app.py
spectran/data_handler.py
spectran/main_ui.py
spectran/main_window.py
spectran/measurement.py
spectran/plots.py
spectran/settings.py
spectran/windows.py
spectran/daq/__init__.py
spectran/daq/daq.py
spectran/daq/nidaqmx.py
spectran/daq/niscope.py
spectran/data/api.html
spectran/data/gear_icon.png
spectran/data/osci_128.ico
spectran-0.5.1.dist-info/LICENSE
spectran-0.5.1.dist-info/METADATA
spectran-0.5.1.dist-info/WHEEL
spectran-0.5.1.dist-info/top_level.txt
spectran-0.5.1.dist-info/RECORD
