Metadata-Version: 2.1
Name: spectran
Version: 0.5.1
Summary: A tool to measure pictures with scale_bars
License: MIT License
Project-URL: repository, https://github.com/ullmannJan/spectran
Classifier: Development Status :: 3 - Alpha
Classifier: Intended Audience :: Science/Research
Classifier: License :: OSI Approved :: MIT License
Classifier: Operating System :: OS Independent
Classifier: Programming Language :: Python :: 3
Classifier: Topic :: Scientific/Engineering :: Visualization
Classifier: Topic :: Utilities
Requires-Python: >=3.10
License-File: LICENSE
Requires-Dist: numpy
Requires-Dist: PySide6
Requires-Dist: pyopengl
Requires-Dist: pyqtgraph
Requires-Dist: pint
Requires-Dist: scipy
Requires-Dist: niscope
Requires-Dist: nisyscfg
Requires-Dist: nidaqmx
Requires-Dist: fastapi
Requires-Dist: uvicorn
Requires-Dist: h5py
Requires-Dist: importlib-metadata ; python_version < "3.11"
Provides-Extra: dev
Requires-Dist: pytest ; extra == 'dev'
